LICENSE
README.md
setup.py
mailchimp_scraper.egg-info/PKG-INFO
mailchimp_scraper.egg-info/SOURCES.txt
mailchimp_scraper.egg-info/dependency_links.txt
mailchimp_scraper.egg-info/requires.txt
mailchimp_scraper.egg-info/top_level.txt
pypi_scraper/__init__.py